{ 
 "nodes": [
    { "id": "DASH", "size":1 },
    { "id": "MCD", "size":1 },
    { "id": "LINK", "size":1 },
    { "id": "INDE", "size":1 },
    { "id": "SBX", "size":1 },
    { "id": "NFX", "size":1 },
    { "id": "EBAY","size":1 },
    { "id": "ZLW", "size":1 },
    { "id": "GGL", "size":1 },
    { "id": "YOU", "size":1 },
    { "id": "AMZ", "size":1 },
    { "id": "YHO", "size":1 },
    { "id": "ZOOM", "size":1 },
    { "id": "FB", "size":1 },
    { "id": "RDDT", "size":1 },
    { "id": "WIKI", "size":1 },
    { "id": "SHOP", "size":1 },
    { "id": "OFFI", "size":1 },
    { "id": "BING", "size":1 },
    { "id": "ALPHA", "size":3 },
    { "id": "MICRO", "size":3 },
    { "id": "FACEB", "size":3 },
    { "id": "ADOBE", "size":3 },
    { "id": "VERIZ", "size":3 },
    { "id": "TWTTR", "size":3 },
    { "id": "COMSC", "size":3 }
  ],
  "links": [
    { "source": "DASH", "target": "ALPHA" },
    { "source": "DASH", "target": "FACEB" },
    { "source": "DASH", "target": "VERIZ" },
    { "source": "MCD", "target": "ALPHA" },
    { "source": "MCD", "target": "MICRO" },
    { "source": "MCD", "target": "ADOBE" },
    { "source": "LINK", "target": "ALPHA" },
    { "source": "LINK", "target": "MICRO" },
    { "source": "LINK", "target": "FACEB" },
    { "source": "LINK", "target": "ADOBE" },
    { "source": "LINK", "target": "TWTTR" },
    { "source": "LINK", "target": "COMSC" },
    { "source": "SBX", "target": "ALPHA" },
    { "source": "SBX", "target": "MICRO" },
    { "source": "NFX", "target": "ALPHA" },
    { "source": "NFX", "target": "FACEB" },
    { "source": "EBAY", "target": "ALPHA" },
    { "source": "ZLW", "target": "ALPHA" },
    { "source": "ZLW", "target": "MICRO" },
    { "source": "ZLW", "target": "FACEB" },
    { "source": "ZLW", "target": "ADOBE" },
    { "source": "ZLW", "target": "VERIZ" },
    { "source": "ZLW", "target": "TWTTR" },
    { "source": "ZLW", "target": "COMSC" },
    { "source": "GGL", "target": "ALPHA" },
    { "source": "YOU", "target": "ALPHA" },
    { "source": "YHO", "target": "ALPHA" },
    { "source": "YHO", "target": "ADOBE" },
    { "source": "YHO", "target": "VERIZ" },
    { "source": "YHO", "target": "TWTTR" },
    { "source": "YHO", "target": "COMSC" },
    { "source": "ZOOM", "target": "ALPHA" },
    { "source": "FB", "target": "FACEB" },
    { "source": "RDDT", "target": "ALPHA" },
    { "source": "RDDT", "target": "COMSC" },
    { "source": "OFFI", "target": "ALPHA" },
    { "source": "OFFI", "target": "MICRO" },
    { "source": "OFFI", "target": "ADOBE" },
    { "source": "OFFI", "target": "VERIZ" },
    { "source": "OFFI", "target": "TWTTR" },
    { "source": "BING", "target": "MICRO" }
  ]
}
